.editorconfig
.gitignore
.gitmodules
.pre-commit-config.yaml
.readthedocs.yml
CONTRIBUTING.rst
LICENSE
README.md
requirements.txt
setup.py
.github/pull_request_template.md
.github/ISSUE_TEMPLATE/bug_report.md
.github/ISSUE_TEMPLATE/enhancement_request.md
.github/workflows/build.yml
.github/workflows/ci.yml
.github/workflows/release.yml
TemporalVAE/__init__.py
TemporalVAE/embryoBetaCell_toyDataset.yaml
TemporalVAE/embryoCell.yaml
TemporalVAE/finetune_u_s_focusEncoder.yaml
TemporalVAE/version.py
TemporalVAE.egg-info/PKG-INFO
TemporalVAE.egg-info/SOURCES.txt
TemporalVAE.egg-info/dependency_links.txt
TemporalVAE.egg-info/requires.txt
TemporalVAE.egg-info/top_level.txt
TemporalVAE/datasets/__init__.py
TemporalVAE/datasets/_datasets.py
TemporalVAE/model_master/RNA_velocity_u_s_Ft_on_s.py
TemporalVAE/model_master/__init__.py
TemporalVAE/model_master/base.py
TemporalVAE/model_master/dataset.py
TemporalVAE/model_master/experiment_RNA_velocity.py
TemporalVAE/model_master/experiment_adversarial.py
TemporalVAE/model_master/experiment_fineTune.py
TemporalVAE/model_master/experiment_fineTune_u_s_focusEncoder.py
TemporalVAE/model_master/experiment_temporalVAE.py
TemporalVAE/model_master/supervise_vanilla_vae_regressionClfDecoder_mouse_noAdversarial.py
TemporalVAE/model_master/supervise_vanilla_vae_regressionClfDecoder_mouse_noAdversarial_u_s_focusEncoder.py
TemporalVAE/model_master/types_.py
TemporalVAE/tools/__init__.py
TemporalVAE/tools/_training.py
TemporalVAE/utils/GPU_manager_pytorch.py
TemporalVAE/utils/__init__.py
TemporalVAE/utils/logging_system.py
TemporalVAE/utils/utils_plot.py
TemporalVAE/utils/utils_project.py
docs/Makefile
docs/make.bat
docs/media/fig1_model_structure.png
docs/source/DynamicalModeling.ipynb
docs/source/_key_contributors.rst
docs/source/about.rst
docs/source/api.rst
docs/source/conf.py
docs/source/getting_started.rst
docs/source/index.rst
docs/source/installation.rst
docs/source/references.bib
docs/source/references.rst
docs/source/release_notes.rst
docs/source/requirements.txt
examples/README.md
examples/TemporalVAE_embryoBetaCells_demo.ipynb
examples/hEmbryo8_Xiang_CV.ipynb
examples/hEmbryo8_training.ipynb
