Metadata-Version: 2.4
Name: TemporalVAE
Version: 1.0.0
Summary: TemporalVAE: Temporal mapping of single cells with time-VAE
Home-page: https://github.com/StatBiomed/TemporalVAE
Author: ['Yijun Liu', 'Yuanhua Huang']
Author-email: yuanhua@hku.hk
License: Apache-2.0
Keywords: Time prediction,Variational autoencoder,Single-cell RNA-seq,Embryogenesis
License-File: LICENSE
Requires-Dist: numpy==1.24.4
Requires-Dist: scipy==1.15.2
Requires-Dist: pandas==2.2.3
Requires-Dist: scikit-learn==1.5.1
Requires-Dist: pynvml==11.5.0
Requires-Dist: gseapy==1.1.9
Requires-Dist: psutil==5.9.5
Requires-Dist: mkl-random==1.2.8
Requires-Dist: torch==2.0.1
Requires-Dist: torchaudio==2.0.2
Requires-Dist: torchvision==0.15.2
Requires-Dist: tensorboard==2.13.0
Requires-Dist: pytorch-lightning==2.0.4
Requires-Dist: matplotlib==3.9.2
Requires-Dist: seaborn==0.13.2
Requires-Dist: matplotlib-venn==1.1.2
Requires-Dist: adjustText==1.3.0
Requires-Dist: scanpy==1.10.3
Requires-Dist: anndata==0.8.0
Requires-Dist: umap-learn==0.5.4
Requires-Dist: tqdm==4.64.1
Provides-Extra: docs
Requires-Dist: sphinx_bootstrap_theme; extra == "docs"
Dynamic: author
Dynamic: author-email
Dynamic: description
Dynamic: description-content-type
Dynamic: home-page
Dynamic: keywords
Dynamic: license
Dynamic: license-file
Dynamic: provides-extra
Dynamic: requires-dist
Dynamic: summary
